torch_roller-0.1.0.dist-info/METADATA
torch_roller-0.1.0.dist-info/WHEEL
torch_roller/__init__.py
torch_roller/convert.py
torch_roller-0.1.0.dist-info/RECORD
