Metadata-Version: 2.1
Name: torch-roller
Version: 0.1.0
Summary: Roll 2d tensor to 3d and vice versa.
Author-Email: Taeyong Jeon <taeyongjeon24@gmail.com>
License: MIT
Requires-Python: >=3.10
Requires-Dist: torch
Requires-Dist: pandas
Requires-Dist: numpy<2
